Workbook

Sheet Dashboard
B2: 📊 SALES PERFORMANCE DASHBOARD | M2: SaaS CRM Analytics
B3: Real-time pipeline tracking · Multi-rep performance · Revenue forecasting
B7: 💰 | F7: 📈 | J7: ✅ | N7: 📦
B8: =SUM(Rep_1!D3:D8,Rep_2!D3:D8,Rep_3!D3:D8) -> 612000 | F8: =SUM(Rep_1!G3:G8,Rep_2!G3:G8,Rep_3!G3:G8) -> 489900 | J8: =SUMIF(All_Deals!F3:F20,"Closed-Won",All_Deals!E3:E20) -> 320000 | N8: =COUNTA(All_Deals!B3:B20) -> 18
B9: TOTAL PIPELINE | F9: PROJECTED REVENUE | J9: CLOSED REVENUE | N9: TOTAL DEALS
B12: ▶ PIPELINE BY STAGE | J12: ▶ REP PERFORMANCE
B13: Stage | D13: Deals | F13: Total Value ($) | H13: Forecast ($) | J13: Rep | K13: Pipeline ($) | L13: Forecast ($) | N13: Closed ($) | P13: vs Target
B14: Lead | D14: =COUNTIF(All_Deals!F3:F20,"Lead") -> 0 | F14: =SUMIF(All_Deals!F3:F20,"Lead",All_Deals!E3:E20) -> 0 | H14: =SUMIF(All_Deals!F3:F20,"Lead",All_Deals!H3:H20) -> 0 | J14: Rep 1 | K14: =SUM(Rep_1!D3:D8) -> 200000 | L14: =SUM(Rep_1!G3:G8) -> 162500 | N14: =SUMIF(Rep_1!E3:E8,"Closed-Won",Rep_1!D3:D8) -> 110000 | P14: =N14/Settings!B12 -> 1.1
B15: Proposal | D15: =COUNTIF(All_Deals!F3:F20,"Proposal") -> 6 | F15: =SUMIF(All_Deals!F3:F20,"Proposal",All_Deals!E3:E20) -> 115000 | H15: =SUMIF(All_Deals!F3:F20,"Proposal",All_Deals!H3:H20) -> 46000 | J15: Rep 2 | K15: =SUM(Rep_2!D3:D8) -> 188000 | L15: =SUM(Rep_2!G3:G8) -> 145100 | N15: =SUMIF(Rep_2!E3:E8,"Closed-Won",Rep_2!D3:D8) -> 85000 | P15: =N15/Settings!B13 -> 1.7
B16: Negotiation | D16: =COUNTIF(All_Deals!F3:F20,"Negotiation") -> 6 | F16: =SUMIF(All_Deals!F3:F20,"Negotiation",All_Deals!E3:E20) -> 177000 | H16: =SUMIF(All_Deals!F3:F20,"Negotiation",All_Deals!H3:H20) -> 123900 | J16: Rep 3 | K16: =SUM(Rep_3!D3:D8) -> 224000 | L16: =SUM(Rep_3!G3:G8) -> 182300 | N16: =SUMIF(Rep_3!E3:E8,"Closed-Won",Rep_3!D3:D8) -> 125000 | P16: =N16/Settings!B14 -> 2.5
B17: Closed-Won | D17: =COUNTIF(All_Deals!F3:F20,"Closed-Won") -> 6 | F17: =SUMIF(All_Deals!F3:F20,"Closed-Won",All_Deals!E3:E20) -> 320000 | H17: =SUMIF(All_Deals!F3:F20,"Closed-Won",All_Deals!H3:H20) -> 320000 | J17: TOTAL | K17: =SUM(K14:K16) -> 612000 | L17: =SUM(L14:L16) -> 489900 | N17: =SUM(N14:N16) -> 320000
B18: Closed-Lost | D18: =COUNTIF(All_Deals!F3:F20,"Closed-Lost") -> 0 | F18: =SUMIF(All_Deals!F3:F20,"Closed-Lost",All_Deals!E3:E20) -> 0 | H18: =SUMIF(All_Deals!F3:F20,"Closed-Lost",All_Deals!H3:H20) -> 0
B19: TOTAL | D19: =SUM(D14:D18) -> 18 | F19: =SUM(F14:F18) -> 612000 | H19: =SUM(H14:H18) -> 489900
B21: ▶ PIPELINE BY STAGE — CHART | J21: ▶ REVENUE BY REP — CHART
B53: Sales CRM Dashboard · All values auto-calculated from Rep_1 / Rep_2 / Rep_3 tabs · Update deals in rep sheets to refresh
A55: Stage | B55: Value | D55: Rep | E55: Pipeline | F55: Forecast | G55: Closed
A56: Lead | B56: =SUMIF(All_Deals!F3:F20,"Lead",All_Deals!E3:E20) -> 0 | D56: Rep 1 | E56: =SUM(Rep_1!D3:D8) -> 200000 | F56: =SUM(Rep_1!G3:G8) -> 162500 | G56: =SUMIF(Rep_1!E3:E8,"Closed-Won",Rep_1!D3:D8) -> 110000
A57: Proposal | B57: =SUMIF(All_Deals!F3:F20,"Proposal",All_Deals!E3:E20) -> 115000 | D57: Rep 2 | E57: =SUM(Rep_2!D3:D8) -> 188000 | F57: =SUM(Rep_2!G3:G8) -> 145100 | G57: =SUMIF(Rep_2!E3:E8,"Closed-Won",Rep_2!D3:D8) -> 85000
A58: Negotiation | B58: =SUMIF(All_Deals!F3:F20,"Negotiation",All_Deals!E3:E20) -> 177000 | D58: Rep 3 | E58: =SUM(Rep_3!D3:D8) -> 224000 | F58: =SUM(Rep_3!G3:G8) -> 182300 | G58: =SUMIF(Rep_3!E3:E8,"Closed-Won",Rep_3!D3:D8) -> 125000
A59: Closed-Won | B59: =SUMIF(All_Deals!F3:F20,"Closed-Won",All_Deals!E3:E20) -> 320000
A60: Closed-Lost | B60: =SUMIF(All_Deals!F3:F20,"Closed-Lost",All_Deals!E3:E20) -> 0

Sheet Rep_1
A1: 📊 Rep 1 — Deal Pipeline
A2: Deal Name | B2: Client | C2: Close Date | D2: Deal Value | E2: Stage | F2: Probability | G2: Forecast
A3: Website Revamp | B3: ABC Ltd | C3: 2026-05-30 | D3: 50000 | E3: Closed-Won | F3: 1 | G3: =D3*F3 -> 50000
A4: Mobile App Development | B4: XYZ Corp | C4: 2026-06-15 | D4: 30000 | E4: Negotiation | F4: 0.7 | G4: =D4*F4 -> 21000
A5: SEO Optimization | B5: Bright Media | C5: 2026-06-20 | D5: 20000 | E5: Proposal | F5: 0.4 | G5: =D5*F5 -> 8000
A6: CRM Integration | B6: NextGen Ltd | C6: 2026-05-28 | D6: 60000 | E6: Closed-Won | F6: 1 | G6: =D6*F6 -> 60000
A7: Website Redesign | B7: Creative Studio | C7: 2026-06-18 | D7: 25000 | E7: Negotiation | F7: 0.7 | G7: =D7*F7 -> 17500
A8: E-commerce Setup | B8: Creative Studio | C8: 2026-06-25 | D8: 15000 | E8: Proposal | F8: 0.4 | G8: =D8*F8 -> 6000
A9: TOTALS | D9: =SUM(D3:D8) -> 200000 | G9: =SUM(G3:G8) -> 162500

Sheet Rep_2
A1: 📊 Rep 2 — Deal Pipeline
A2: Deal Name | B2: Client | C2: Close Date | D2: Deal Value | E2: Stage | F2: Probability | G2: Forecast
A3: Data Dashboard | B3: Insight Inc | C3: 2026-05-29 | D3: 40000 | E3: Closed-Won | F3: 1 | G3: =D3*F3 -> 40000
A4: Automation System | B4: AutoFlow | C4: 2026-06-22 | D4: 35000 | E4: Negotiation | F4: 0.7 | G4: =D4*F4 -> 24500
A5: Cloud Migration | B5: Prime Tech | C5: 2026-06-19 | D5: 18000 | E5: Proposal | F5: 0.4 | G5: =D5*F5 -> 7200
A6: Financial Software | B6: FinCore | C6: 2026-05-27 | D6: 45000 | E6: Closed-Won | F6: 1 | G6: =D6*F6 -> 45000
A7: Marketing Campaign | B7: MarketPro | C7: 2026-06-24 | D7: 28000 | E7: Negotiation | F7: 0.7 | G7: =D7*F7 -> 19600
A8: Retail Platform | B8: RetailHub | C8: 2026-06-21 | D8: 22000 | E8: Proposal | F8: 0.4 | G8: =D8*F8 -> 8800
A9: TOTALS | D9: =SUM(D3:D8) -> 188000 | G9: =SUM(G3:G8) -> 145100

Sheet Rep_3
A1: 📊 Rep 3 — Deal Pipeline
A2: Deal Name | B2: Client | C2: Close Date | D2: Deal Value | E2: Stage | F2: Probability | G2: Forecast
A3: Analytics Platform | B3: DataWorks | C3: 2026-05-26 | D3: 55000 | E3: Closed-Won | F3: 1 | G3: =D3*F3 -> 55000
A4: Construction ERP | B4: BuildTech | C4: 2026-06-23 | D4: 32000 | E4: Negotiation | F4: 0.7 | G4: =D4*F4 -> 22400
A5: Brand Strategy | B5: Brandify | C5: 2026-06-20 | D5: 21000 | E5: Proposal | F5: 0.4 | G5: =D5*F5 -> 8400
A6: Cloud Infrastructure | B6: CloudNet | C6: 2026-05-25 | D6: 70000 | E6: Closed-Won | F6: 1 | G6: =D6*F6 -> 70000
A7: UI/UX Redesign | B7: DesignPro | C7: 2026-06-26 | D7: 27000 | E7: Negotiation | F7: 0.7 | G7: =D7*F7 -> 18900
A8: Retail Expansion | B8: ShopSmart | C8: 2026-06-28 | D8: 19000 | E8: Proposal | F8: 0.4 | G8: =D8*F8 -> 7600
A9: TOTALS | D9: =SUM(D3:D8) -> 224000 | G9: =SUM(G3:G8) -> 182300

Sheet All_Deals
A1: 📋 Master Deal List — All Reps
A2: Rep | B2: Deal Name | C2: Client | D2: Close Date | E2: Deal Value | F2: Stage | G2: Probability | H2: Forecast
A3: Rep 1 | B3: Website Revamp | C3: ABC Ltd | D3: 2026-05-30 | E3: 50000 | F3: Closed-Won | G3: 1 | H3: 50000
A4: Rep 1 | B4: Mobile App Development | C4: XYZ Corp | D4: 2026-06-15 | E4: 30000 | F4: Negotiation | G4: 0.7 | H4: 21000
A5: Rep 1 | B5: SEO Optimization | C5: Bright Media | D5: 2026-06-20 | E5: 20000 | F5: Proposal | G5: 0.4 | H5: 8000
A6: Rep 1 | B6: CRM Integration | C6: NextGen Ltd | D6: 2026-05-28 | E6: 60000 | F6: Closed-Won | G6: 1 | H6: 60000
A7: Rep 1 | B7: Website Redesign | C7: Creative Studio | D7: 2026-06-18 | E7: 25000 | F7: Negotiation | G7: 0.7 | H7: 17500
A8: Rep 1 | B8: E-commerce Setup | C8: Creative Studio | D8: 2026-06-25 | E8: 15000 | F8: Proposal | G8: 0.4 | H8: 6000
A9: Rep 2 | B9: Data Dashboard | C9: Insight Inc | D9: 2026-05-29 | E9: 40000 | F9: Closed-Won | G9: 1 | H9: 40000
A10: Rep 2 | B10: Automation System | C10: AutoFlow | D10: 2026-06-22 | E10: 35000 | F10: Negotiation | G10: 0.7 | H10: 24500
A11: Rep 2 | B11: Cloud Migration | C11: Prime Tech | D11: 2026-06-19 | E11: 18000 | F11: Proposal | G11: 0.4 | H11: 7200
A12: Rep 2 | B12: Financial Software | C12: FinCore | D12: 2026-05-27 | E12: 45000 | F12: Closed-Won | G12: 1 | H12: 45000
A13: Rep 2 | B13: Marketing Campaign | C13: MarketPro | D13: 2026-06-24 | E13: 28000 | F13: Negotiation | G13: 0.7 | H13: 19600
A14: Rep 2 | B14: Retail Platform | C14: RetailHub | D14: 2026-06-21 | E14: 22000 | F14: Proposal | G14: 0.4 | H14: 8800
... A20: Rep 3 | B20: Retail Expansion | C20: ShopSmart | D20: 2026-06-28 | E20: 19000 | F20: Proposal | G20: 0.4 | H20: 7600

Sheet Settings
A1: ⚙️ Configuration Settings
A2: Recipient Email | B2: reports@company.com
A3: Email Subject | B3: Weekly Sales Dashboard Report
A4: Stage Probability Table | B4: Probability
A5: Lead
A6: Proposal | B6: 0.4
A7: Negotiation | B7: 0.7
A8: Closed-Won | B8: 1
A9: Closed-Lost | B9: 0
A11: Sales Targets | B11: Monthly Target ($)
A12: Rep_1 | B12: 100000
A13: Rep_2 | B13: 50000
A14: Rep_3 | B14: 50000

Sheet Apps_Script_Code
A1: 📜 Google Apps Script — Copy this code into Extensions > Apps Script
A2: /**
A3: * ============================================================
A4: * Sales Team Tracking Tool — Google Apps Script
A5: * Bound to: Sales_Tracker spreadsheet
A6: * Author: [Suhaj Ahmad]
A8: * ============================================================
A9: */
A11: // ── CONSTANTS ─────────────────────────────────────────────
A12: const SETTINGS_SHEET = "Settings";
A13: const DASHBOARD_SHEET = "Dashboard";
A14: const EMAIL_CELL = "B3"; // Recipient email in Settings
... A218: }
